MANIFEST.in
README.md
config.py
constants.py
db.py
deputy-complete.sh
deputy.py
encryption.py
exceptions.py
functions.py
help_texts.py
s.py
setup.py
validators.py
dpos_deputy.egg-info/PKG-INFO
dpos_deputy.egg-info/SOURCES.txt
dpos_deputy.egg-info/dependency_links.txt
dpos_deputy.egg-info/entry_points.txt
dpos_deputy.egg-info/requires.txt
dpos_deputy.egg-info/top_level.txt