Metadata-Version: 1.0
Name: dpos-deputy
Version: 0.0.37
Summary: CLI for managing dpos delegates
Home-page: https://github.com/BlockHub/dpos-deputy
Author: Charles
Author-email: karel@blockhub.nl
License: MIT
Platform: UNKNOWN
